mlos_viz/__init__.py
mlos_viz/base.py
mlos_viz/dabl.py
mlos_viz/py.typed
mlos_viz/util.py
mlos_viz/version.py
mlos_viz-0.6.2.dist-info/METADATA
mlos_viz-0.6.2.dist-info/WHEEL
mlos_viz-0.6.2.dist-info/top_level.txt
mlos_viz-0.6.2.dist-info/RECORD
