Metadata-Version: 2.1
Name: mlos-viz
Version: 0.6.2
Summary: Visualization Python interface for benchmark automation and optimization results.
Author-email: Microsoft <mlos-maintainers@service.microsoft.com>
Maintainer-email: Microsoft <mlos-maintainers@service.microsoft.com>
License: MIT
Project-URL: Documentation, https://microsoft.github.io/MLOS/source_tree_docs/mlos_viz/
Project-URL: Repository, https://github.com/microsoft/MLOS/
Project-URL: Issues, https://github.com/microsoft/MLOS/issues
Project-URL: Package Source, https://github.com/microsoft/MLOS/tree/main/mlos_viz/
Keywords: autotuning,benchmarking,optimization,systems,visualization
Classifier: Intended Audience :: Developers
Classifier: Intended Audience :: Science/Research
Classifier: Intended Audience :: System Administrators
Classifier: License :: OSI Approved :: MIT License
Classifier: Operating System :: OS Independent
Classifier: Programming Language :: Python :: 3
Classifier: Programming Language :: Python :: 3.10
Classifier: Programming Language :: Python :: 3.11
Classifier: Programming Language :: Python :: 3.12
Classifier: Programming Language :: Python :: 3.13
Requires-Python: >=3.10
Requires-Dist: mlos-bench==0.6.2
Requires-Dist: dabl>=0.3.2
Requires-Dist: matplotlib
Requires-Dist: seaborn>=0.12.2
Provides-Extra: full
Provides-Extra: full-tests
Requires-Dist: pytest; extra == "full-tests"
Requires-Dist: pytest-forked; extra == "full-tests"
Requires-Dist: pytest-xdist; extra == "full-tests"
Requires-Dist: pytest-cov; extra == "full-tests"
Requires-Dist: pytest-local-badge; extra == "full-tests"
